poibin/__init__.py
poibin/poibin.py
pypcurve/__init__.py
pypcurve/pypcurve.py
pypcurve-0.1.1.dist-info/LICENSE.md
pypcurve-0.1.1.dist-info/METADATA
pypcurve-0.1.1.dist-info/WHEEL
pypcurve-0.1.1.dist-info/top_level.txt
pypcurve-0.1.1.dist-info/RECORD
