Metadata-Version: 2.1
Name: pypcurve
Version: 0.1.1
Summary: A Python library for p-curve estimation
Home-page: https://github.com/QuentinAndre/pypcurve/
Author: Quentin André
Author-email: quentin.andre@colorado.edu
License: MIT
Keywords: mediation-analysis,statistics,process,plotting,data-science,data-analysis,data-visualization,regression-models
Classifier: Programming Language :: Python
Classifier: License :: OSI Approved
Classifier: Natural Language :: English
Classifier: Development Status :: 4 - Beta
Classifier: Operating System :: OS Independent
Classifier: Programming Language :: Python :: 3.7
Requires-Python: >=3.7
License-File: LICENSE.md
Requires-Dist: numpy
Requires-Dist: matplotlib
Requires-Dist: pandas
Requires-Dist: scipy
Requires-Dist: seaborn
